flask_pynamodb_resource/__init__.py
flask_pynamodb_resource-1.2.1.dist-info/LICENSE.txt
flask_pynamodb_resource-1.2.1.dist-info/METADATA
flask_pynamodb_resource-1.2.1.dist-info/WHEEL
flask_pynamodb_resource-1.2.1.dist-info/top_level.txt
flask_pynamodb_resource-1.2.1.dist-info/version.txt
flask_pynamodb_resource-1.2.1.dist-info/version_full.txt
flask_pynamodb_resource-1.2.1.dist-info/RECORD
