Metadata-Version: 2.1
Name: flask-pynamodb-resource
Version: 1.2.1
Summary: Presents PynamoDB models (DynamoDB tables) as Flask-RESTX resources
Home-page: https://github.com/brandond/flask-pynamodb-resource
Author: Brandon Davidson
Author-email: brad@oatmail.org
License: UNKNOWN
Platform: UNKNOWN
Classifier: Development Status :: 4 - Beta
Classifier: Framework :: Flask
Classifier: License :: OSI Approved :: Apache Software License
Classifier: Programming Language :: Python :: 2.7
Classifier: Programming Language :: Python :: 3.5
Classifier: Programming Language :: Python :: 3.6
Classifier: Programming Language :: Python :: 3.7
Classifier: Topic :: Database :: Front-Ends
Requires-Python: >=2.7
Requires-Dist: flask-restx
Requires-Dist: pynamodb
Requires-Dist: six
Provides-Extra: dev
Requires-Dist: setuptools-version-command ; extra == 'dev'
